metaoptim/__init__.py
metaoptim/bench_func.py
metaoptim/config.py
metaoptim/pso/__init__.py
metaoptim/pso/gbest_pso.py
metaoptim/pso/pso.py
open_metaoptim-0.0.14.dist-info/LICENSE
open_metaoptim-0.0.14.dist-info/METADATA
open_metaoptim-0.0.14.dist-info/WHEEL
open_metaoptim-0.0.14.dist-info/top_level.txt
open_metaoptim-0.0.14.dist-info/RECORD
