Metadata-Version: 2.1
Name: open-metaoptim
Version: 0.0.14
Summary: A Python package for metaheuristic optimisation.
Home-page: https://github.com/harrymyburgh/metaoptim
Author: Harry Phillip Myburgh
Author-email: harry.myburgh@gmail.com
Project-URL: Bug Tracker, https://github.com/harrymyburgh/metaoptim/issues
Classifier: Programming Language :: Python :: 3
Classifier: License :: OSI Approved :: MIT License
Classifier: Operating System :: OS Independent
Requires-Python: >=3.9
License-File: LICENSE
Requires-Dist: numpy (>=1.23.0)
Requires-Dist: numba (>=0.56.0)
Requires-Dist: tqdm (>=4.64.0)
Provides-Extra: dev
Requires-Dist: pytest (>=7.2.0) ; extra == 'dev'
Requires-Dist: check-manifest (>=0.49) ; extra == 'dev'
Requires-Dist: twine (>=4.0.2) ; extra == 'dev'
Requires-Dist: pycodestyle (>=2.10.0) ; extra == 'dev'
